slakonet/__init__.py
slakonet-2025.8.1.dist-info/licenses/LICENSE
slakonet-2025.8.1.dist-info/METADATA
slakonet-2025.8.1.dist-info/WHEEL
slakonet-2025.8.1.dist-info/top_level.txt
slakonet-2025.8.1.dist-info/RECORD
