Metadata-Version: 2.4
Name: slakonet
Version: 2025.8.1
Summary: slakonet
Home-page: https://github.com/atomgptlab/slakonet
Author: Kamal Choudhary
Author-email: kchoudh2@jhu.edu
Classifier: Programming Language :: Python :: 3
Classifier: License :: OSI Approved :: MIT License
Classifier: Operating System :: OS Independent
Requires-Python: >=3.10
License-File: LICENSE
Dynamic: author
Dynamic: author-email
Dynamic: classifier
Dynamic: description
Dynamic: description-content-type
Dynamic: home-page
Dynamic: license-file
Dynamic: requires-python
Dynamic: summary
